perceval_interop/__init__.py
perceval_interop/abstract_converter.py
perceval_interop/cqasm/__init__.py
perceval_interop/cqasm/cqasm_converter.py
perceval_interop/myqlm/__init__.py
perceval_interop/myqlm/myqlm_converter.py
perceval_interop/myqlm/myqlm_helper.py
perceval_interop/myqlm/qpu_handler.py
perceval_interop/qiskit/__init__.py
perceval_interop/qiskit/circuit_to_graph_converter.py
perceval_interop/qiskit/converter_statevector.py
perceval_interop/qiskit/qiskit_converter.py
perceval_interop/qiskit/resources_estimator.py
perceval_interop/utils/__init__.py
perceval_interop/utils/converter_utils.py
perceval_interop/utils/exceptions.py
perceval_interop/utils/metadata.py
perceval_interop-1.2.0.dist-info/licenses/LICENSE
perceval_interop-1.2.0.dist-info/METADATA
perceval_interop-1.2.0.dist-info/WHEEL
perceval_interop-1.2.0.dist-info/top_level.txt
perceval_interop-1.2.0.dist-info/RECORD
