Metadata-Version: 2.4
Name: perceval-interop
Version: 1.2.0
Summary: Interoperability packages between Perceval and other quantum computing frameworks
Home-page: https://github.com/Quandela/Perceval_Interop
Author: quandela
Project-URL: Documentation, https://perceval.quandela.net/interopdocs/
Project-URL: Source, https://github.com/Quandela/Perceval_Interop
Project-URL: Tracker, https://github.com/Quandela/Perceval_Interop/issues
Classifier: Programming Language :: Python :: 3.9
Classifier: Programming Language :: Python :: 3.10
Classifier: Programming Language :: Python :: 3.11
Classifier: Programming Language :: Python :: 3.12
Classifier: Programming Language :: Python :: 3.13
Classifier: License :: OSI Approved :: MIT License
Classifier: Operating System :: OS Independent
Requires-Python: >=3.9,<3.14
License-File: LICENSE
Requires-Dist: perceval-quandela~=1.0.1
Provides-Extra: qiskit
Requires-Dist: qiskit~=2.1.2; extra == "qiskit"
Requires-Dist: seaborn~=0.13; extra == "qiskit"
Provides-Extra: qutip
Requires-Dist: qutip~=5.0.4; extra == "qutip"
Provides-Extra: myqlm
Requires-Dist: myqlm~=1.11.3; extra == "myqlm"
Provides-Extra: cqasm
Requires-Dist: libqasm==1.2.1; extra == "cqasm"
Provides-Extra: all
Requires-Dist: qiskit~=2.1.2; extra == "all"
Requires-Dist: seaborn~=0.13; extra == "all"
Requires-Dist: qutip~=5.0.4; extra == "all"
Requires-Dist: myqlm~=1.11.3; extra == "all"
Requires-Dist: libqasm==1.2.1; extra == "all"
Dynamic: author
Dynamic: classifier
Dynamic: description
Dynamic: description-content-type
Dynamic: home-page
Dynamic: license-file
Dynamic: project-url
Dynamic: provides-extra
Dynamic: requires-dist
Dynamic: requires-python
Dynamic: summary
